sensorylab_smeller-0.1.83.dist-info/licenses/LICENSE
smeller/__init__.py
smeller/commands/__init__.py
smeller/commands/base.py
smeller/commands/channel_control.py
smeller/commands/command_factory.py
smeller/commands/get_help.py
smeller/commands/misc_commands.py
smeller/commands/restart_device.py
smeller/commands/set_aroma_params.py
smeller/commands/set_channel_params.py
smeller/commands/set_generator.py
smeller/communication/__init__.py
smeller/communication/base.py
smeller/communication/bluetooth_com.py
smeller/communication/factory.py
smeller/communication/mqtt_com.py
smeller/communication/multi_device_manager.py
smeller/communication/serial_com.py
smeller/config/__init__.py
smeller/config/config.py
smeller/config/config_manager.py
smeller/config/constants.py
smeller/controllers/__init__.py
smeller/controllers/aromablock_model_controller.py
smeller/controllers/cartridge_manager.py
smeller/controllers/device_controller.py
smeller/database/__init__.py
smeller/database/db_manager.py
smeller/dynamic_control/__init__.py
smeller/dynamic_control/aroma_table_model.py
smeller/dynamic_control/dynamic_block_controller.py
smeller/dynamic_control/view_model.py
smeller/gui/__init__.py
smeller/gui/connectors.py
smeller/gui/main_window.py
smeller/gui/theme_manager.py
smeller/gui/ui_manager.py
smeller/gui/aromablocks/__init__.py
smeller/gui/aromablocks/aroma_block_delegate.py
smeller/gui/aromablocks/aroma_block_dialog.py
smeller/gui/aromablocks/aroma_block_list.py
smeller/gui/cartridges/__init__.py
smeller/gui/cartridges/cartridge_info_dialog.py
smeller/gui/channels/__init__.py
smeller/gui/channels/channel_button.py
smeller/gui/channels/channel_manager.py
smeller/gui/control_panel/__init__.py
smeller/gui/control_panel/control_panel.py
smeller/gui/control_panel/seconds_time_edit.py
smeller/gui/control_panel/timeline_player.py
smeller/gui/mediacenter/__init__.py
smeller/gui/mediacenter/aromablock_timeline_widget.py
smeller/gui/mediacenter/integrated_player.py
smeller/gui/mediacenter/media_view.py
smeller/gui/menu_bar/__init__.py
sensorylab_smeller-0.1.83.dist-info/METADATA
sensorylab_smeller-0.1.83.dist-info/WHEEL
sensorylab_smeller-0.1.83.dist-info/top_level.txt
sensorylab_smeller-0.1.83.dist-info/RECORD
