Metadata-Version: 2.4
Name: sensorylab-smeller
Version: 0.1.83
Summary: Python library for Neuroair device control
Home-page: http://10.10.0.20:3000/SensoryLAB/smeller
Author: SensoryLAB
Author-email: fox@sensorylab.ru
License: MIT
Classifier: Programming Language :: Python :: 3
Classifier: License :: OSI Approved :: MIT License
Classifier: Operating System :: OS Independent
Classifier: Topic :: Scientific/Engineering :: Interface Engine/Protocol Translator
Classifier: Topic :: Software Development :: Libraries :: Python Modules
Requires-Python: >=3.10
License-File: LICENSE
Requires-Dist: future>=1.0.0
Requires-Dist: iso8601>=2.1.0
Requires-Dist: pybluez2>=0.46
Requires-Dist: pyserial>=3.5
Requires-Dist: PyYAML>=6.0.2
Requires-Dist: paho-mqtt==2.1.0
Provides-Extra: gui
Requires-Dist: PyQt6; extra == "gui"
Requires-Dist: PyQtGraph; extra == "gui"
Dynamic: author
Dynamic: author-email
Dynamic: classifier
Dynamic: description
Dynamic: description-content-type
Dynamic: home-page
Dynamic: license
Dynamic: license-file
Dynamic: provides-extra
Dynamic: requires-dist
Dynamic: requires-python
Dynamic: summary
